article_playground/__init__.py
article_playground/__main__.py
article_playground/client.py
article_playground/logger.py
article_playground/notion/__init__.py
article_playground/notion/endpoints/__init__.py
article_playground/notion/endpoints/databases.py
article_playground/notion/service.py
article_playground/types.py
article_playground-0.2.1.dist-info/entry_points.txt
article_playground-0.2.1.dist-info/WHEEL
article_playground-0.2.1.dist-info/METADATA
article_playground-0.2.1.dist-info/RECORD
