Metadata-Version: 2.1
Name: article-playground
Version: 0.2.1
Summary: 
Author: socar-grab
Author-email: grab@socar.kr
Requires-Python: >=3.9,<4.0
Classifier: Programming Language :: Python :: 3
Classifier: Programming Language :: Python :: 3.10
Classifier: Programming Language :: Python :: 3.9
Requires-Dist: httpx (>=0.22.0,<0.23.0)
Requires-Dist: key (>=0.4,<0.5)
Requires-Dist: mypy (>=0.931,<0.932)
Requires-Dist: pydantic (>=1.9.0,<2.0.0)
Requires-Dist: pytest (>=6.2.5,<7.0.0)
Requires-Dist: requests (>=2.27.1,<3.0.0)
